gofile2/__init__.py
gofile2/errors.py
gofile2/gofile2.py
gofile2/gofile2_sync.py
gofile2-1.5.2.dist-info/LICENSE
gofile2-1.5.2.dist-info/METADATA
gofile2-1.5.2.dist-info/WHEEL
gofile2-1.5.2.dist-info/top_level.txt
gofile2-1.5.2.dist-info/RECORD
