Metadata-Version: 2.1
Name: gofile2
Version: 1.5.2
Summary: An API wrapper for Gofile API
Home-page: https://github.com/Itz-fork/Gofile2
Download-URL: https://github.com/Itz-fork/Gofile2/releases/tag/Gofile2-v1.5.2
Author: Itz-fork, Codec04
Author-email: itz-fork@users.noreply.github.com
License: MIT
Keywords: Gofile,Api-wrapper,Gofile2
Classifier: Development Status :: 5 - Production/Stable
Classifier: Intended Audience :: Developers
Classifier: Topic :: Education
Classifier: License :: OSI Approved :: MIT License
Classifier: Programming Language :: Python :: 3.7
Classifier: Programming Language :: Python :: 3.8
Classifier: Programming Language :: Python :: 3.9
Classifier: Programming Language :: Python :: 3.10
Classifier: Programming Language :: Python :: 3.11
License-File: LICENSE
Requires-Dist: aiohttp
Requires-Dist: aiofiles
